remote_email_filtering/__init__.py
remote_email_filtering/action.py
remote_email_filtering/auth.py
remote_email_filtering/main.py
remote_email_filtering/message.py
remote_email_filtering/remote.py
remote_email_filtering/types.py
remote_email_filtering-0.2.4.dist-info/COPYING
remote_email_filtering-0.2.4.dist-info/METADATA
remote_email_filtering-0.2.4.dist-info/WHEEL
remote_email_filtering-0.2.4.dist-info/RECORD
